pmidcite/__init__.py
pmidcite/cfg.py
pmidcite/cfgini.py
pmidcite/citation.py
pmidcite/pubmedqueryicite.py
pmidcite/summarize_papers.py
pmidcite/utils_module.py
pmidcite/cli/__init__.py
pmidcite/cli/common.py
pmidcite/cli/dnldpubmed.py
pmidcite/cli/entry_keyset.py
pmidcite/cli/icite.py
pmidcite/cli/readpmids.py
pmidcite/cli/rptdatestop.py
pmidcite/cli/summarize_papers.py
pmidcite/cli/utils.py
pmidcite/eutils/__init__.py
pmidcite/eutils/apikey.py
pmidcite/eutils/cmds/__init__.py
pmidcite/eutils/cmds/base.py
pmidcite/eutils/cmds/elink.py
pmidcite/eutils/cmds/esearch.py
pmidcite/eutils/cmds/pubmed.py
pmidcite/eutils/cmds/query_ids.py
pmidcite/eutils/pubmed/__init__.py
pmidcite/eutils/pubmed/author.py
pmidcite/eutils/pubmed/authors.py
pmidcite/eutils/pubmed/descriptors.py
pmidcite/eutils/pubmed/qualifiers.py
pmidcite/eutils/pubmed/query.py
pmidcite/eutils/pubmed/rdwr.py
pmidcite/eutils/pubmed/record.py
pmidcite/eutils/pubmed/terms.py
pmidcite/eutils/pubmed/counts/__init__.py
pmidcite/eutils/pubmed/counts/data.py
pmidcite/eutils/pubmed/counts/dnld.py
pmidcite/eutils/pubmed/counts/dnlded_data.py
pmidcite/eutils/pubmed/counts/plt.py
pmidcite/eutils/pubmed/counts/prt.py
pmidcite/icite/__init__.py
pmidcite/icite/api.py
pmidcite/icite/downloader.py
pmidcite/icite/entry.py
pmidcite/icite/nih_grouper.py
pmidcite/icite/paper.py
pmidcite/icite/papers.py
pmidcite/icite/pmid_dnlder.py
pmidcite/icite/prt_hdrkey.py
pmidcite/icite/top_cit_ref.py
pmidcite/icite/utils.py
pmidcite/icite/dnldr/__init__.py
pmidcite/icite/dnldr/pmid_dnlder.py
pmidcite/icite/dnldr/pmid_dnlder_base.py
pmidcite/icite/dnldr/pmid_dnlder_only.py
pmidcite/icite/dnldr/pmid_loader.py
pmidcite/plot/__init__.py
pmidcite/plot/nih_perc.py
pmidcite/plot/scatter.py
pmidcite/scripts/__init__.py
pmidcite/scripts/icite.py
pmidcite/scripts/summarize_papers.py
pmidcite-0.3.1.dist-info/licenses/LICENSE
pmidcite-0.3.1.dist-info/METADATA
pmidcite-0.3.1.dist-info/WHEEL
pmidcite-0.3.1.dist-info/entry_points.txt
pmidcite-0.3.1.dist-info/top_level.txt
pmidcite-0.3.1.dist-info/RECORD
