Metadata-Version: 2.4
Name: pmidcite
Version: 0.3.1
Summary: Turbocharge a PubMed literature search using citation data from the NIH
Author-email: "DV Klopfenstein, PhD" <dvklopfenstein@protonmail.com>
Maintainer-email: "DV Klopfenstein, PhD" <dvklopfenstein@protonmail.com>
License-Expression: AGPL-3.0-or-later
Project-URL: Homepage, https://github.com/dvklopfenstein/pmidcite
Project-URL: Changelog, https://github.com/dvklopfenstein/pmidcite/blob/main/CHANGELOG.md
Project-URL: Code, https://github.com/dvklopfenstein/pmidcite
Project-URL: Issue tracker, https://github.com/dvklopfenstein/pmidcite/issues
Keywords: library,pubmed,ncbi,command-line-tool,literature-mining,citations,Citation-network,google-search,google-scholar
Classifier: Development Status :: 5 - Production/Stable
Classifier: Topic :: Scientific/Engineering :: Information Analysis
Classifier: Topic :: Scientific/Engineering :: Bio-Informatics
Classifier: Intended Audience :: Science/Research
Classifier: Intended Audience :: Developers
Classifier: Intended Audience :: Information Technology
Classifier: Environment :: Console
Classifier: Programming Language :: Python
Classifier: Programming Language :: Python :: 3
Classifier: Programming Language :: Python :: 3.9
Classifier: Programming Language :: Python :: 3.10
Classifier: Programming Language :: Python :: 3.11
Classifier: Programming Language :: Python :: 3.12
Classifier: Programming Language :: Python :: 3.13
Classifier: Programming Language :: Python :: 3 :: Only
Classifier: Operating System :: POSIX :: Linux
Classifier: Operating System :: POSIX
Classifier: Operating System :: Unix
Classifier: Operating System :: MacOS
Requires-Python: >=3.9
License-File: LICENSE
Requires-Dist: requests
Dynamic: license-file
